setup.py
astropost/__init__.py
astropost/interfaces.py
astropost.egg-info/PKG-INFO
astropost.egg-info/SOURCES.txt
astropost.egg-info/dependency_links.txt
astropost.egg-info/requires.txt
astropost.egg-info/top_level.txt