Metadata-Version: 1.1
Name: astropost
Version: 0.1
Summary: Commenting API for Australian news sites
Home-page: http://github.com/murodese/astropost
Author: James Meneghello
Author-email: murodese@gmail.com
License: UNKNOWN
Download-URL: https://github.com/Murodese/astropost/archive/master.zip
Platform: UNKNOWN
